LAB5/comparator_2bit.vhd
library IEEE;
use IEEE.STD_LOGIC_1164.ALL;
use IEEE.NUMERIC_STD.ALL;

entity COMPARATOR_2BIT is
    Port (
        A  : in  STD_LOGIC_VECTOR(1 downto 0);
        B  : in  STD_LOGIC_VECTOR(1 downto 0);
        EQ : out STD_LOGIC;  -- A = B
        GT : out STD_LOGIC;  -- A > B
        LT : out STD_LOGIC   -- A < B
    );
end entity COMPARATOR_2BIT;

architecture Behavioral of COMPARATOR_2BIT is
begin
    process(A, B)
    begin
        if unsigned(A) = unsigned(B) then
            EQ <= '1';
            GT <= '0';
            LT <= '0';

        elsif unsigned(A) > unsigned(B) then
            EQ <= '0';
            GT <= '1';
            LT <= '0';

        else
            EQ <= '0';
            GT <= '0';
            LT <= '1';
        end if;
    end process;
end architecture Behavioral;

LAB5/tb_comparator_2bit.vhd
library IEEE;
use IEEE.STD_LOGIC_1164.ALL;
use IEEE.NUMERIC_STD.ALL;

entity TB_COMPARATOR_2BIT is
end entity TB_COMPARATOR_2BIT;

architecture Simulation of TB_COMPARATOR_2BIT is

    signal A  : STD_LOGIC_VECTOR(1 downto 0) := "00";
    signal B  : STD_LOGIC_VECTOR(1 downto 0) := "00";
    signal EQ : STD_LOGIC;
    signal GT : STD_LOGIC;
    signal LT : STD_LOGIC;

begin

    DUT : entity work.COMPARATOR_2BIT
        port map (
            A  => A,
            B  => B,
            EQ => EQ,
            GT => GT,
            LT => LT
        );

    STIMULUS : process
    begin
        -- Loop through all possible combinations of A and B (16 cases)
        for i in 0 to 3 loop
            for j in 0 to 3 loop
                A <= std_logic_vector(to_unsigned(i, 2));
                B <= std_logic_vector(to_unsigned(j, 2));
                wait for 10 ns;
            end loop;
        end loop;

        wait;
    end process STIMULUS;

end architecture Simulation;

LAB5/simulation.vcd
$date
  Wed Jul 01 11:49:58 2026
$end
$version
  GHDL v0
$end
$timescale
  1 fs
$end
$scope module standard $end
$upscope $end
$scope module std_logic_1164 $end
$upscope $end
$scope module numeric_std $end
$upscope $end
$scope module tb_comparator_2bit $end
$var reg 2 ! a[1:0] $end
$var reg 2 " b[1:0] $end
$var reg 1 # eq $end
$var reg 1 $ gt $end
$var reg 1 % lt $end
$scope module dut $end
$var reg 2 & a[1:0] $end
$var reg 2 ' b[1:0] $end
$var reg 1 ( eq $end
$var reg 1 ) gt $end
$var reg 1 * lt $end
$upscope $end
$upscope $end
$enddefinitions $end
#0
b00 !
b00 "
1#
0$
0%
b00 &
b00 '
1(
0)
0*
#10000000
b01 "
0#
1%
b01 '
0(
1*
#20000000
b10 "
b10 '
#30000000
b11 "
b11 '
#40000000
b01 !
b00 "
1$
0%
b01 &
b00 '
1)
0*
#50000000
b01 "
1#
0$
b01 '
1(
0)
#60000000
b10 "
0#
1%
b10 '
0(
1*
#70000000
b11 "
b11 '
#80000000
b10 !
b00 "
1$
0%
b10 &
b00 '
1)
0*
#90000000
b01 "
b01 '
#100000000
b10 "
1#
0$
b10 '
1(
0)
#110000000
b11 "
0#
1%
b11 '
0(
1*
#120000000
b11 !
b00 "
1$
0%
b11 &
b00 '
1)
0*
#130000000
b01 "
b01 '
#140000000
b10 "
b10 '
#150000000
b11 "
1#
0$
b11 '
1(
0)
